sLOUT/__init__.py
sLOUT/clearScreen.py
sLOUT/fetchToken.py
sLOUT/log.py
sLOUT/readConfig.py
sLOUT/readFile.py
sLOUT/time.py
sLOUT/writeConfig.py
sLOUT/writeFile.py
sLOUT/writePy.py
sLOUT-0.4.0.dist-info/LICENSE
sLOUT-0.4.0.dist-info/METADATA
sLOUT-0.4.0.dist-info/WHEEL
sLOUT-0.4.0.dist-info/top_level.txt
sLOUT-0.4.0.dist-info/RECORD
